1_RTL/4_COMB_LOGIC/1_MUX/mux.v
`timescale 1ns / 1ps

module mux(
	// port list
	i_tx0			,
	i_rx0			,
	i_pwm1			,
	i_other_signal		,
	i_select		,
	o_data_out
);
	
	// port delcaration
	input i_tx0				;
	input i_rx0				;
	input i_pwm1				;
	input i_other_signal			;
	input [1:0] i_select			;	
	output o_data_out			;
	
	// modeling
	reg o_data_out;	
	always@(*) begin
		case(i_select)
			0 : o_data_out = i_tx0		;
			1 : o_data_out = i_rx0		;
			2 : o_data_out = i_pwm1		;
			3 : o_data_out = i_other_signal	;	
			default: o_data_out = 1'bz	;
		endcase
	end

endmodule

1_RTL/4_COMB_LOGIC/1_MUX/tb_mux.v
`timescale 1ns / 1ps

module tb_mux;

	// stimulus: connected to input(active)				;
	reg 	  i_tx0				;
	reg 	  i_rx0				;	
	reg       i_pwm1			;
	reg       i_other_signal		;
	reg       [1:0] i_select	;
	// monitor signal: connected to output(passive)
	wire o_data_out				;
	
	// dut instantiation
	mux dut(
	.i_tx0			(i_tx0)			,
	.i_rx0			(i_rx0)			,
	.i_pwm1			(i_pwm1)		,
	.i_other_signal		(i_other_signal)	,
	.i_select		(i_select)		,	
	.o_data_out		(o_data_out)
);
		
	// dumpfile gen
	initial begin
		$dumpfile("./mux.vcd")	;
		$dumpvars(0, tb_mux)	;
	end
		
	// apply stimulus	
	initial begin
		i_select = 2'd0; i_tx0 = 1'b0; i_rx0 = 1'b0; i_pwm1 = 1'b0; i_other_signal = 1'b0; #10;
                i_select = 2'd0; i_tx0 = 1'b1; i_rx0 = 1'b0; i_pwm1 = 1'b0; i_other_signal = 1'b0; #10;
                i_select = 2'd0; i_tx0 = 1'b0; i_rx0 = 1'b1; i_pwm1 = 1'b0; i_other_signal = 1'b0; #10;
                i_select = 2'd0; i_tx0 = 1'b0; i_rx0 = 1'b0; i_pwm1 = 1'b1; i_other_signal = 1'b0; #10;
                i_select = 2'd0; i_tx0 = 1'b0; i_rx0 = 1'b0; i_pwm1 = 1'b0; i_other_signal = 1'b1; #10;

		i_select = 2'd1; i_tx0 = 1'b0; i_rx0 = 1'b0; i_pwm1 = 1'b0; i_other_signal = 1'b0; #10;
                i_select = 2'd1; i_tx0 = 1'b1; i_rx0 = 1'b0; i_pwm1 = 1'b0; i_other_signal = 1'b0; #10;
                i_select = 2'd1; i_tx0 = 1'b0; i_rx0 = 1'b1; i_pwm1 = 1'b0; i_other_signal = 1'b0; #10;
                i_select = 2'd1; i_tx0 = 1'b0; i_rx0 = 1'b0; i_pwm1 = 1'b1; i_other_signal = 1'b0; #10;
                i_select = 2'd1; i_tx0 = 1'b0; i_rx0 = 1'b0; i_pwm1 = 1'b0; i_other_signal = 1'b1; #10;
		
		i_select = 2'd2; i_tx0 = 1'b0; i_rx0 = 1'b0; i_pwm1 = 1'b0; i_other_signal = 1'b0; #10;
                i_select = 2'd2; i_tx0 = 1'b1; i_rx0 = 1'b0; i_pwm1 = 1'b0; i_other_signal = 1'b0; #10;
                i_select = 2'd2; i_tx0 = 1'b0; i_rx0 = 1'b1; i_pwm1 = 1'b0; i_other_signal = 1'b0; #10;
                i_select = 2'd2; i_tx0 = 1'b0; i_rx0 = 1'b0; i_pwm1 = 1'b1; i_other_signal = 1'b0; #10;
                i_select = 2'd2; i_tx0 = 1'b0; i_rx0 = 1'b0; i_pwm1 = 1'b0; i_other_signal = 1'b1; #10;
		
		i_select = 2'd3; i_tx0 = 1'b0; i_rx0 = 1'b0; i_pwm1 = 1'b0; i_other_signal = 1'b0; #10;
                i_select = 2'd3; i_tx0 = 1'b1; i_rx0 = 1'b0; i_pwm1 = 1'b0; i_other_signal = 1'b0; #10;
                i_select = 2'd3; i_tx0 = 1'b0; i_rx0 = 1'b1; i_pwm1 = 1'b0; i_other_signal = 1'b0; #10;
                i_select = 2'd3; i_tx0 = 1'b0; i_rx0 = 1'b0; i_pwm1 = 1'b1; i_other_signal = 1'b0; #10;
                i_select = 2'd3; i_tx0 = 1'b0; i_rx0 = 1'b0; i_pwm1 = 1'b0; i_other_signal = 1'b1; #10;

		$finish;
	end

endmodule

1_RTL/4_COMB_LOGIC/1_MUX/mux.vcd
$date
    Aug 12, 2026  20:55:36
$end
$version
    TOOL:	xmsim(64)	22.03-s012
$end
$timescale
    1 ps
$end

$scope module tb_mux $end
$var reg       1 !    i_tx0 $end
$var reg       1 "    i_rx0 $end
$var reg       1 #    i_pwm1 $end
$var reg       1 $    i_other_signal $end
$var reg       2 %    i_select [1:0] $end
$var wire      1 &    o_data_out  $end

$scope module dut $end
$var wire      1 '    i_tx0  $end
$var wire      1 (    i_rx0  $end
$var wire      1 )    i_pwm1  $end
$var wire      1 *    i_other_signal  $end
$var wire      2 +    i_select [1:0] $end
$var reg       1 ,    o_data_out $end
$upscope $end

$upscope $end

$enddefinitions $end
$dumpvars
0!
0"
0#
0$
b0 %
0&
0'
0(
0)
0*
b0 +
0,
$end
#10000
1!
1'
1,
1&
#20000
0!
1"
1(
0'
0,
0&
#30000
0"
1#
1)
0(
#40000
0#
1$
1*
0)
#50000
b1 %
0$
0*
b1 +
#60000
1!
1'
#70000
0!
1"
1(
0'
1,
1&
#80000
0"
1#
1)
0(
0,
0&
#90000
0#
1$
1*
0)
#100000
b10 %
0$
0*
b10 +
#110000
1!
1'
#120000
0!
1"
1(
0'
#130000
0"
1#
1)
0(
1,
1&
#140000
0#
1$
1*
0)
0,
0&
#150000
b11 %
0$
0*
b11 +
#160000
1!
1'
#170000
0!
1"
1(
0'
#180000
0"
1#
1)
0(
#190000
0#
1$
1*
0)
1,
1&
