1_RTL/2_TINY_PROJECT/Protocol/UART/UART_TX/Sync_FIFO.v
`timescale 1ns / 1ps

module Sync_FIFO #(
	parameter DATA_WIDTH = 8						,
	parameter DEPTH      = 16
)(
	clk									,
	rst_n									,
	wr_en									,	
	rd_en									,
	wr_data									,
	rd_data									,
	full									,
	empty		
)										;

	localparam ADDR_WIDTH = $clog2(DEPTH);

	input clk								;
	input rst_n								;	
	input wr_en								;
	input rd_en								;
	input  [DATA_WIDTH-1:0] wr_data						;
	output [DATA_WIDTH-1:0] rd_data						;
	output full								;
	output empty								;

	reg [DATA_WIDTH-1:0] mem [0:DEPTH-1]  					;
	reg [ADDR_WIDTH:0] wr_ptr						;
	reg [ADDR_WIDTH:0] rd_ptr						;

	assign full  = (wr_ptr[ADDR_WIDTH] != rd_ptr[ADDR_WIDTH]) &&
                   (wr_ptr[ADDR_WIDTH-1:0] == rd_ptr[ADDR_WIDTH-1:0])		;
    	
	assign empty = (wr_ptr == rd_ptr)					;

	// write
	always@(posedge clk or negedge rst_n) begin
		if(!rst_n)              wr_ptr <= 0				;
		else if(wr_en && !full) wr_ptr <= wr_ptr + 1			;
	end
	
	always@(posedge clk) begin
		if(wr_en && !full) mem[wr_ptr[ADDR_WIDTH-1:0]] <= wr_data	;
	end
	// read
	always@(posedge clk or negedge rst_n) begin
        	if(!rst_n)               rd_ptr <= 0				;
        	else if(rd_en && !empty) rd_ptr <= rd_ptr + 1			;
   	end
	
	assign rd_data = mem[rd_ptr[ADDR_WIDTH-1:0]] 				;

endmodule

1_RTL/2_TINY_PROJECT/Protocol/UART/UART_TX/uart_tx.v
`timescale 1ns / 1ps

module uart_tx #(
parameter DATA_WIDTH = 8				,
parameter DEPTH = 16)
(
	clk						,	
	rst_n						,
	baud_tick					,
	tx_data						,
	tx_valid					,
	tx_ready					,
	tx_full						,
	tx_empty					,
	tx
)							;

	input clk					;
	input rst_n					;
	input baud_tick 				;
	input [DATA_WIDTH-1:0] tx_data  		;
	input tx_valid					;
	output tx_ready					;
	output tx_full					;
	output tx_empty					;
	output tx					;

	reg tx						;
	assign tx_ready = ~tx_full                      ;
	
	reg fifo_rd_en					;
	wire [DATA_WIDTH-1:0] fifo_rd_data		;

	Sync_FIFO #(.DATA_WIDTH(DATA_WIDTH), .DEPTH(DEPTH)) tx_fifo(
	.clk(clk)					,
	.rst_n(rst_n)					,
	.wr_en(tx_valid && tx_ready)			,
	.rd_en(fifo_rd_en)				,
	.wr_data(tx_data)				,
	.rd_data(fifo_rd_data)				,
	.full(tx_full)					,
	.empty(tx_empty))				;

	localparam IDLE   = 3'b000			;  
	localparam START  = 3'b001			;
	localparam DATA   = 3'b010			;
	localparam PARITY = 3'b011			;
	localparam STOP   = 3'b100			;

	reg [2:0]                    state		;
	reg [2:0]                    next_state		;
	reg [$clog2(DATA_WIDTH)-1:0] bit_cnt		;
	reg [DATA_WIDTH-1:0]         tx_data_reg	;
	reg                          parity_bit		;

	// State register (sequential)
	always@(posedge clk or negedge rst_n) begin
		if(!rst_n) state <= IDLE		;
		else       state <= next_state		;

	end

	// Next state logic (combinational)
	always@(*) begin
		next_state = state			;
		fifo_rd_en = 1'b0			;	
		case(state) 
			IDLE    : if(!tx_empty && baud_tick) begin 
			          	fifo_rd_en = 1'b1							; 
					next_state = START							; 
				  end 	
			START   : if(baud_tick)                          	      next_state = DATA		;
			DATA    : if(baud_tick && bit_cnt == DATA_WIDTH-1)            next_state = PARITY	;				      
			PARITY  : if(baud_tick)                          	      next_state = STOP	        ;
			STOP    : if(baud_tick) begin
                                  	if(!tx_empty) begin
						fifo_rd_en = 1'b1						;
						next_state = START						;
					end
					else    next_state = IDLE						;
				  end
			default : 					              next_state = IDLE		;
		endcase 
	end

	// Output logic / datapath (sequential)
	always@(posedge clk or negedge rst_n) begin
		if(!rst_n) begin
			tx            <= 1'b1								;
			tx_data_reg   <= 0								;
			bit_cnt       <= 0								;
			parity_bit    <= 0								;
		end
		else begin
			case(state)
				IDLE    : begin 
						tx          <= 1'b1					;	 
						bit_cnt     <= 0					;  	
						tx_data_reg <= 0					;
						parity_bit  <= 0					;
					  end
                        	START   : begin
						tx            <= 1'b0                       		;
						tx_data_reg   <= fifo_rd_data				;
						parity_bit    <= ^fifo_rd_data				;
					  end
                        	DATA    : begin
						tx <= tx_data_reg[bit_cnt]				;
						if(baud_tick) bit_cnt <= bit_cnt +1			;
					  end                       
                        	PARITY  : tx <= parity_bit                     	  			;
                        	STOP    : begin
					  	tx      <= 1'b1                       			;
						bit_cnt <= 0						;
					  end
				default : tx <= 1'b1							;
			endcase
		end
	end

endmodule

1_RTL/2_TINY_PROJECT/Protocol/UART/UART_TX/tb_uart_tx.v
`timescale 1ns / 1ps

module tb_uart_tx;
	parameter DATA_WIDTH = 8                      ;
	parameter DEPTH      = 16		      ;
	parameter BAUD_DIV   = 20		      ;
	reg clk                                       ;
        reg rst_n                                     ;
        reg baud_tick                                 ;
        reg [DATA_WIDTH-1:0] tx_data                  ;
        reg tx_valid                                  ;
        wire tx_ready                                 ;
        wire tx_full                                  ;
        wire tx_empty                                 ;
        wire tx					      ;
	
	integer errors     = 0			      ;
    	integer baud_cnt			      ;
	integer i				      ;
	integer bit_i				      ;
	reg [DATA_WIDTH-1:0] rx_data		      ;
	reg rx_parity				      ;
	reg rx_stop				      ;


	uart_tx #(.DATA_WIDTH(DATA_WIDTH), .DEPTH(DEPTH)) dut ( 
        .clk(clk)                                     ,
        .rst_n(rst_n)                                 ,
        .baud_tick(baud_tick)                         ,
        .tx_data(tx_data)                             ,
        .tx_valid(tx_valid)                           ,
        .tx_ready(tx_ready)                           ,
        .tx_full(tx_full)                             ,
        .tx_empty(tx_empty)                           ,
        .tx(tx))				      ;

	initial clk = 1'b0			      ;
    	always #5 clk = ~clk	      		      ;
	
    	always @(posedge clk or negedge rst_n) begin
        	if (!rst_n) begin
            		baud_cnt  <= 0;
            		baud_tick <= 1'b0;
        	end 
		else if (baud_cnt == BAUD_DIV-1) begin
            		baud_cnt  <= 0;
            		baud_tick <= 1'b1;
        	end 
		else begin
            		baud_cnt  <= baud_cnt + 1;
            		baud_tick <= 1'b0;
        	end
    	end

	task send_byte;
        	input [DATA_WIDTH-1:0] data;
        	begin
            		@(negedge clk);
            		tx_data = data; tx_valid = 1;
            		@(negedge clk);
            		while (!tx_ready) @(negedge clk);
            		tx_valid = 0;
        	end
    	endtask
    	
	task check_frame;
        	input [DATA_WIDTH-1:0] expected;
        	begin
   			@(negedge tx);                       // start bit
            		@(posedge baud_tick); #1;
            		for (bit_i = 0; bit_i < DATA_WIDTH; bit_i = bit_i + 1) begin
                		rx_data[bit_i] = tx;
                		@(posedge baud_tick); #1;
            		end
            		rx_parity = tx;
            		@(posedge baud_tick); #1;             // move to stop bit
            		rx_stop = tx;

			if (rx_data !== expected) begin
                		errors = errors + 1;
                		$display("[%0t] FAIL DATA exp=%h got=%h", $time, expected, rx_data);
            		end
            		if (rx_parity !== ^expected) begin
                		errors = errors + 1;
                		$display("[%0t] FAIL PARITY exp=%b got=%b", $time, ^expected, rx_parity);
            		end
            		if (rx_stop !== 1'b1) begin
                		errors = errors + 1;
                		$display("[%0t] FAIL STOP bit not 1", $time);
            		end
            		if ((rx_data === expected) && (rx_parity === ^expected) && (rx_stop === 1'b1))
                		$display("[%0t] PASS data=%h", $time, expected);
        		end
    	endtask

	initial begin
        	rst_n = 0; tx_valid = 0; tx_data = 0;
        	repeat (5) @(posedge clk);
        	rst_n = 1;
 
        	for (i = 0; i < 4; i = i + 1) begin
            		send_byte(i * 8'h55);
            		check_frame(i * 8'h55);
        	end
 
        	repeat (BAUD_DIV*12) @(posedge clk);
        	if (errors == 0) $display("ALL TESTS PASSED");
        	else              $display("%0d ERRORS", errors);
        	$finish;
    	end
 
    	initial begin
        	$dumpfile("tb_uart_tx.vcd");
        	$dumpvars(0, tb_uart_tx);
    	end
	
endmodule

1_RTL/2_TINY_PROJECT/Protocol/UART/UART_TX/tb_uart_tx.vcd
$date
    Sep  8, 2026  03:53:32
$end
$version
    TOOL:	xmsim(64)	22.03-s012
$end
$timescale
    1 ps
$end

$scope module tb_uart_tx $end
$var parameter 32 !    DATA_WIDTH $end
$var parameter 32 "    DEPTH $end
$var parameter 32 #    BAUD_DIV $end
$var reg       1 $    clk $end
$var reg       1 %    rst_n $end
$var reg       1 &    baud_tick $end
$var reg       8 '    tx_data [7:0] $end
$var reg       1 (    tx_valid $end
$var wire      1 )    tx_ready  $end
$var wire      1 *    tx_full  $end
$var wire      1 +    tx_empty  $end
$var wire      1 ,    tx  $end
$var integer  32 -    errors $end
$var integer  32 .    baud_cnt $end
$var integer  32 /    i $end
$var integer  32 0    bit_i $end
$var reg       8 1    rx_data [7:0] $end
$var reg       1 2    rx_parity $end
$var reg       1 3    rx_stop $end

$scope module dut $end
$var parameter 32 4    DATA_WIDTH $end
$var parameter 32 5    DEPTH $end
$var wire      1 6    clk  $end
$var wire      1 7    rst_n  $end
$var wire      1 8    baud_tick  $end
$var wire      8 9    tx_data [7:0] $end
$var wire      1 :    tx_valid  $end
$var wire      1 )    tx_ready  $end
$var wire      1 *    tx_full  $end
$var wire      1 +    tx_empty  $end
$var reg       1 ;    tx $end
$var reg       1 <    fifo_rd_en $end
$var wire      8 =    fifo_rd_data [7:0] $end
$var parameter  3 >    IDLE $end
$var parameter  3 ?    START $end
$var parameter  3 @    DATA $end
$var parameter  3 A    PARITY $end
$var parameter  3 B    STOP $end
$var reg       3 C    state [2:0] $end
$var reg       3 D    next_state [2:0] $end
$var reg       3 E    bit_cnt [2:0] $end
$var reg       8 F    tx_data_reg [7:0] $end
$var reg       1 G    parity_bit $end

$scope module tx_fifo $end
$var parameter 32 H    DATA_WIDTH $end
$var parameter 32 I    DEPTH $end
$var parameter 32 J    ADDR_WIDTH $end
$var wire      1 6    clk  $end
$var wire      1 7    rst_n  $end
$var wire      1 K    wr_en  $end
$var wire      1 L    rd_en  $end
$var wire      8 9    wr_data [7:0] $end
$var reg       8 M    rd_data [7:0] $end
$var wire      1 *    full  $end
$var wire      1 +    empty  $end
$var reg       8 N    mem[0] [7:0] $end
$var reg       8 O    mem[1] [7:0] $end
$var reg       8 P    mem[2] [7:0] $end
$var reg       8 Q    mem[3] [7:0] $end
$var reg       8 R    mem[4] [7:0] $end
$var reg       8 S    mem[5] [7:0] $end
$var reg       8 T    mem[6] [7:0] $end
$var reg       8 U    mem[7] [7:0] $end
$var reg       8 V    mem[8] [7:0] $end
$var reg       8 W    mem[9] [7:0] $end
$var reg       8 X    mem[10] [7:0] $end
$var reg       8 Y    mem[11] [7:0] $end
$var reg       8 Z    mem[12] [7:0] $end
$var reg       8 [    mem[13] [7:0] $end
$var reg       8 \    mem[14] [7:0] $end
$var reg       8 ]    mem[15] [7:0] $end
$var reg       5 ^    wr_ptr [4:0] $end
$var reg       5 _    rd_ptr [4:0] $end
$upscope $end

$upscope $end


$scope task send_byte $end
$var reg       8 `    data [7:0] $end
$upscope $end


$scope task check_frame $end
$var reg       8 a    expected [7:0] $end
$upscope $end

$upscope $end

$enddefinitions $end
$dumpvars
b100 J
b10000 I
b1000 H
b100 B
b11 A
b10 @
b1 ?
b0 >
b10000 5
b1000 4
b10100 #
b10000 "
b1000 !
0$
0%
0&
b0 '
0(
1)
0*
1+
1,
b0 -
b0 .
bx /
bx 0
bx 1
x2
x3
06
07
08
b0 9
0:
1;
0<
bx =
b0 C
b0 D
b0 E
b0 F
0G
0K
0L
bx M
bx N
bx O
bx P
bx Q
bx R
bx S
bx T
bx U
bx V
bx W
bx X
bx Y
bx Z
bx [
bx \
bx ]
b0 ^
b0 _
bx `
bx a
$end
#5000
1$
16
#10000
0$
06
#15000
1$
16
#20000
0$
06
#25000
1$
16
#30000
0$
06
#35000
1$
16
#40000
0$
06
#45000
1$
1%
b0 /
b0 `
17
16
#50000
0$
1(
1:
06
1K
#55000
1$
16
b1 .
b0 N
b1 ^
0+
#60000
0$
0(
b0 a
0:
06
0K
#65000
1$
16
b10 .
#70000
0$
06
#75000
1$
16
b11 .
#80000
0$
06
#85000
1$
16
b100 .
#90000
0$
06
#95000
1$
16
b101 .
#100000
0$
06
#105000
1$
16
b110 .
#110000
0$
06
#115000
1$
16
b111 .
#120000
0$
06
#125000
1$
16
b1000 .
#130000
0$
06
#135000
1$
16
b1001 .
#140000
0$
06
#145000
1$
16
b1010 .
#150000
0$
06
#155000
1$
16
b1011 .
#160000
0$
06
#165000
1$
16
b1100 .
#170000
0$
06
#175000
1$
16
b1101 .
#180000
0$
06
#185000
1$
16
b1110 .
#190000
0$
06
#195000
1$
16
b1111 .
#200000
0$
06
#205000
1$
16
b10000 .
#210000
0$
06
#215000
1$
16
b10001 .
#220000
0$
06
#225000
1$
16
b10010 .
#230000
0$
06
#235000
1$
16
b10011 .
#240000
0$
06
#245000
1$
16
b0 .
1&
18
1<
b1 D
1L
#250000
0$
06
#255000
1$
16
b1 .
0&
b1 C
b0 M
b1 _
0<
b10 D
0L
1+
08
b0 =
b1 D
#260000
0$
06
#265000
1$
16
b10 .
0;
0,
#270000
0$
06
#275000
1$
16
b11 .
#280000
0$
06
#285000
1$
16
b100 .
#290000
0$
06
#295000
1$
16
b101 .
#300000
0$
06
#305000
1$
16
b110 .
#310000
0$
06
#315000
1$
16
b111 .
#320000
0$
06
#325000
1$
16
b1000 .
#330000
0$
06
#335000
1$
16
b1001 .
#340000
0$
06
#345000
1$
16
b1010 .
#350000
0$
06
#355000
1$
16
b1011 .
#360000
0$
06
#365000
1$
16
b1100 .
#370000
0$
06
#375000
1$
16
b1101 .
#380000
0$
06
#385000
1$
16
b1110 .
#390000
0$
06
#395000
1$
16
b1111 .
#400000
0$
06
#405000
1$
16
b10000 .
#410000
0$
06
#415000
1$
16
b10001 .
#420000
0$
06
#425000
1$
16
b10010 .
#430000
0$
06
#435000
1$
16
b10011 .
#440000
0$
06
#445000
1$
16
b0 .
1&
18
b10 D
#446000
b0 0
bx0 1
#450000
0$
06
#455000
1$
16
b1 .
0&
b10 C
08
#460000
0$
06
#465000
1$
16
b10 .
#470000
0$
06
#475000
1$
16
b11 .
#480000
0$
06
#485000
1$
16
b100 .
#490000
0$
06
#495000
1$
16
b101 .
#500000
0$
06
#505000
1$
16
b110 .
#510000
0$
06
#515000
1$
16
b111 .
#520000
0$
06
#525000
1$
16
b1000 .
#530000
0$
06
#535000
1$
16
b1001 .
#540000
0$
06
#545000
1$
16
b1010 .
#550000
0$
06
#555000
1$
16
b1011 .
#560000
0$
06
#565000
1$
16
b1100 .
#570000
0$
06
#575000
1$
16
b1101 .
#580000
0$
06
#585000
1$
16
b1110 .
#590000
0$
06
#595000
1$
16
b1111 .
#600000
0$
06
#605000
1$
16
b10000 .
#610000
0$
06
#615000
1$
16
b10001 .
#620000
0$
06
#625000
1$
16
b10010 .
#630000
0$
06
#635000
1$
16
b10011 .
#640000
0$
06
#645000
1$
16
b0 .
1&
18
#646000
b1 0
bx00 1
#650000
0$
06
#655000
1$
16
b1 .
0&
b1 E
08
#660000
0$
06
#665000
1$
16
b10 .
#670000
0$
06
#675000
1$
16
b11 .
#680000
0$
06
#685000
1$
16
b100 .
#690000
0$
06
#695000
1$
16
b101 .
#700000
0$
06
#705000
1$
16
b110 .
#710000
0$
06
#715000
1$
16
b111 .
#720000
0$
06
#725000
1$
16
b1000 .
#730000
0$
06
#735000
1$
16
b1001 .
#740000
0$
06
#745000
1$
16
b1010 .
#750000
0$
06
#755000
1$
16
b1011 .
#760000
0$
06
#765000
1$
16
b1100 .
#770000
0$
06
#775000
1$
16
b1101 .
#780000
0$
06
#785000
1$
16
b1110 .
#790000
0$
06
#795000
1$
16
b1111 .
#800000
0$
06
#805000
1$
16
b10000 .
#810000
0$
06
#815000
1$
16
b10001 .
#820000
0$
06
#825000
1$
16
b10010 .
#830000
0$
06
#835000
1$
16
b10011 .
#840000
0$
06
#845000
1$
16
b0 .
1&
18
#846000
b10 0
bx000 1
#850000
0$
06
#855000
1$
16
b1 .
0&
b10 E
08
#860000
0$
06
#865000
1$
16
b10 .
#870000
0$
06
#875000
1$
16
b11 .
#880000
0$
06
#885000
1$
16
b100 .
#890000
0$
06
#895000
1$
16
b101 .
#900000
0$
06
#905000
1$
16
b110 .
#910000
0$
06
#915000
1$
16
b111 .
#920000
0$
06
#925000
1$
16
b1000 .
#930000
0$
06
#935000
1$
16
b1001 .
#940000
0$
06
#945000
1$
16
b1010 .
#950000
0$
06
#955000
1$
16
b1011 .
#960000
0$
06
#965000
1$
16
b1100 .
#970000
0$
06
#975000
1$
16
b1101 .
#980000
0$
06
#985000
1$
16
b1110 .
#990000
0$
06
#995000
1$
16
b1111 .
#1000000
0$
06
#1005000
1$
16
b10000 .
#1010000
0$
06
#1015000
1$
16
b10001 .
#1020000
0$
06
#1025000
1$
16
b10010 .
#1030000
0$
06
#1035000
1$
16
b10011 .
#1040000
0$
06
#1045000
1$
16
b0 .
1&
18
#1046000
b11 0
bx0000 1
#1050000
0$
06
#1055000
1$
16
b1 .
0&
b11 E
08
#1060000
0$
06
#1065000
1$
16
b10 .
#1070000
0$
06
#1075000
1$
16
b11 .
#1080000
0$
06
#1085000
1$
16
b100 .
#1090000
0$
06
#1095000
1$
16
b101 .
#1100000
0$
06
#1105000
1$
16
b110 .
#1110000
0$
06
#1115000
1$
16
b111 .
#1120000
0$
06
#1125000
1$
16
b1000 .
#1130000
0$
06
#1135000
1$
16
b1001 .
#1140000
0$
06
#1145000
1$
16
b1010 .
#1150000
0$
06
#1155000
1$
16
b1011 .
#1160000
0$
06
#1165000
1$
16
b1100 .
#1170000
0$
06
#1175000
1$
16
b1101 .
#1180000
0$
06
#1185000
1$
16
b1110 .
#1190000
0$
06
#1195000
1$
16
b1111 .
#1200000
0$
06
#1205000
1$
16
b10000 .
#1210000
0$
06
#1215000
1$
16
b10001 .
#1220000
0$
06
#1225000
1$
16
b10010 .
#1230000
0$
06
#1235000
1$
16
b10011 .
#1240000
0$
06
#1245000
1$
16
b0 .
1&
18
#1246000
b100 0
bx00000 1
#1250000
0$
06
#1255000
1$
16
b1 .
0&
b100 E
08
#1260000
0$
06
#1265000
1$
16
b10 .
#1270000
0$
06
#1275000
1$
16
b11 .
#1280000
0$
06
#1285000
1$
16
b100 .
#1290000
0$
06
#1295000
1$
16
b101 .
#1300000
0$
06
#1305000
1$
16
b110 .
#1310000
0$
06
#1315000
1$
16
b111 .
#1320000
0$
06
#1325000
1$
16
b1000 .
#1330000
0$
06
#1335000
1$
16
b1001 .
#1340000
0$
06
#1345000
1$
16
b1010 .
#1350000
0$
06
#1355000
1$
16
b1011 .
#1360000
0$
06
#1365000
1$
16
b1100 .
#1370000
0$
06
#1375000
1$
16
b1101 .
#1380000
0$
06
#1385000
1$
16
b1110 .
#1390000
0$
06
#1395000
1$
16
b1111 .
#1400000
0$
06
#1405000
1$
16
b10000 .
#1410000
0$
06
#1415000
1$
16
b10001 .
#1420000
0$
06
#1425000
1$
16
b10010 .
#1430000
0$
06
#1435000
1$
16
b10011 .
#1440000
0$
06
#1445000
1$
16
b0 .
1&
18
#1446000
b101 0
bx000000 1
#1450000
0$
06
#1455000
1$
16
b1 .
0&
b101 E
08
#1460000
0$
06
#1465000
1$
16
b10 .
#1470000
0$
06
#1475000
1$
16
b11 .
#1480000
0$
06
#1485000
1$
16
b100 .
#1490000
0$
06
#1495000
1$
16
b101 .
#1500000
0$
06
#1505000
1$
16
b110 .
#1510000
0$
06
#1515000
1$
16
b111 .
#1520000
0$
06
#1525000
1$
16
b1000 .
#1530000
0$
06
#1535000
1$
16
b1001 .
#1540000
0$
06
#1545000
1$
16
b1010 .
#1550000
0$
06
#1555000
1$
16
b1011 .
#1560000
0$
06
#1565000
1$
16
b1100 .
#1570000
0$
06
#1575000
1$
16
b1101 .
#1580000
0$
06
#1585000
1$
16
b1110 .
#1590000
0$
06
#1595000
1$
16
b1111 .
#1600000
0$
06
#1605000
1$
16
b10000 .
#1610000
0$
06
#1615000
1$
16
b10001 .
#1620000
0$
06
#1625000
1$
16
b10010 .
#1630000
0$
06
#1635000
1$
16
b10011 .
#1640000
0$
06
#1645000
1$
16
b0 .
1&
18
#1646000
b110 0
bx0000000 1
#1650000
0$
06
#1655000
1$
16
b1 .
0&
b110 E
08
#1660000
0$
06
#1665000
1$
16
b10 .
#1670000
0$
06
#1675000
1$
16
b11 .
#1680000
0$
06
#1685000
1$
16
b100 .
#1690000
0$
06
#1695000
1$
16
b101 .
#1700000
0$
06
#1705000
1$
16
b110 .
#1710000
0$
06
#1715000
1$
16
b111 .
#1720000
0$
06
#1725000
1$
16
b1000 .
#1730000
0$
06
#1735000
1$
16
b1001 .
#1740000
0$
06
#1745000
1$
16
b1010 .
#1750000
0$
06
#1755000
1$
16
b1011 .
#1760000
0$
06
#1765000
1$
16
b1100 .
#1770000
0$
06
#1775000
1$
16
b1101 .
#1780000
0$
06
#1785000
1$
16
b1110 .
#1790000
0$
06
#1795000
1$
16
b1111 .
#1800000
0$
06
#1805000
1$
16
b10000 .
#1810000
0$
06
#1815000
1$
16
b10001 .
#1820000
0$
06
#1825000
1$
16
b10010 .
#1830000
0$
06
#1835000
1$
16
b10011 .
#1840000
0$
06
#1845000
1$
16
b0 .
1&
18
#1846000
b111 0
b0 1
#1850000
0$
06
#1855000
1$
16
b1 .
0&
b111 E
b11 D
08
b10 D
#1860000
0$
06
#1865000
1$
16
b10 .
#1870000
0$
06
#1875000
1$
16
b11 .
#1880000
0$
06
#1885000
1$
16
b100 .
#1890000
0$
06
#1895000
1$
16
b101 .
#1900000
0$
06
#1905000
1$
16
b110 .
#1910000
0$
06
#1915000
1$
16
b111 .
#1920000
0$
06
#1925000
1$
16
b1000 .
#1930000
0$
06
#1935000
1$
16
b1001 .
#1940000
0$
06
#1945000
1$
16
b1010 .
#1950000
0$
06
#1955000
1$
16
b1011 .
#1960000
0$
06
#1965000
1$
16
b1100 .
#1970000
0$
06
#1975000
1$
16
b1101 .
#1980000
0$
06
#1985000
1$
16
b1110 .
#1990000
0$
06
#1995000
1$
16
b1111 .
#2000000
0$
06
#2005000
1$
16
b10000 .
#2010000
0$
06
#2015000
1$
16
b10001 .
#2020000
0$
06
#2025000
1$
16
b10010 .
#2030000
0$
06
#2035000
1$
16
b10011 .
#2040000
0$
06
#2045000
1$
16
b0 .
1&
18
b11 D
#2046000
b1000 0
02
#2050000
0$
06
#2055000
1$
16
b1 .
0&
b0 E
b11 C
b100 D
08
b11 D
#2060000
0$
06
#2065000
1$
16
b10 .
#2070000
0$
06
#2075000
1$
16
b11 .
#2080000
0$
06
#2085000
1$
16
b100 .
#2090000
0$
06
#2095000
1$
16
b101 .
#2100000
0$
06
#2105000
1$
16
b110 .
#2110000
0$
06
#2115000
1$
16
b111 .
#2120000
0$
06
#2125000
1$
16
b1000 .
#2130000
0$
06
#2135000
1$
16
b1001 .
#2140000
0$
06
#2145000
1$
16
b1010 .
#2150000
0$
06
#2155000
1$
16
b1011 .
#2160000
0$
06
#2165000
1$
16
b1100 .
#2170000
0$
06
#2175000
1$
16
b1101 .
#2180000
0$
06
#2185000
1$
16
b1110 .
#2190000
0$
06
#2195000
1$
16
b1111 .
#2200000
0$
06
#2205000
1$
16
b10000 .
#2210000
0$
06
#2215000
1$
16
b10001 .
#2220000
0$
06
#2225000
1$
16
b10010 .
#2230000
0$
06
#2235000
1$
16
b10011 .
#2240000
0$
06
#2245000
1$
16
b0 .
1&
18
b100 D
#2246000
03
b1 -
b1 /
b1010101 `
#2250000
0$
b1010101 '
1(
1:
b1010101 9
06
1K
#2255000
1$
16
b1 .
0&
b100 C
b1010101 O
b10 ^
b0 D
0+
08
b100 D
#2260000
0$
0(
b1010101 a
0:
06
0K
#2265000
1$
16
b10 .
1;
1,
#2270000
0$
06
#2275000
1$
16
b11 .
#2280000
0$
06
#2285000
1$
16
b100 .
#2290000
0$
06
#2295000
1$
16
b101 .
#2300000
0$
06
#2305000
1$
16
b110 .
#2310000
0$
06
#2315000
1$
16
b111 .
#2320000
0$
06
#2325000
1$
16
b1000 .
#2330000
0$
06
#2335000
1$
16
b1001 .
#2340000
0$
06
#2345000
1$
16
b1010 .
#2350000
0$
06
#2355000
1$
16
b1011 .
#2360000
0$
06
#2365000
1$
16
b1100 .
#2370000
0$
06
#2375000
1$
16
b1101 .
#2380000
0$
06
#2385000
1$
16
b1110 .
#2390000
0$
06
#2395000
1$
16
b1111 .
#2400000
0$
06
#2405000
1$
16
b10000 .
#2410000
0$
06
#2415000
1$
16
b10001 .
#2420000
0$
06
#2425000
1$
16
b10010 .
#2430000
0$
06
#2435000
1$
16
b10011 .
#2440000
0$
06
#2445000
1$
16
b0 .
1&
18
1<
b1 D
1L
#2450000
0$
06
#2455000
1$
16
b1 .
0&
b1 C
b1010101 M
b10 _
0<
b10 D
0L
1+
08
b1010101 =
b1 D
#2460000
0$
06
#2465000
1$
16
b10 .
0;
b1010101 F
0,
#2470000
0$
06
#2475000
1$
16
b11 .
#2480000
0$
06
#2485000
1$
16
b100 .
#2490000
0$
06
#2495000
1$
16
b101 .
#2500000
0$
06
#2505000
1$
16
b110 .
#2510000
0$
06
#2515000
1$
16
b111 .
#2520000
0$
06
#2525000
1$
16
b1000 .
#2530000
0$
06
#2535000
1$
16
b1001 .
#2540000
0$
06
#2545000
1$
16
b1010 .
#2550000
0$
06
#2555000
1$
16
b1011 .
#2560000
0$
06
#2565000
1$
16
b1100 .
#2570000
0$
06
#2575000
1$
16
b1101 .
#2580000
0$
06
#2585000
1$
16
b1110 .
#2590000
0$
06
#2595000
1$
16
b1111 .
#2600000
0$
06
#2605000
1$
16
b10000 .
#2610000
0$
06
#2615000
1$
16
b10001 .
#2620000
0$
06
#2625000
1$
16
b10010 .
#2630000
0$
06
#2635000
1$
16
b10011 .
#2640000
0$
06
#2645000
1$
16
b0 .
1&
18
b10 D
#2646000
b0 0
#2650000
0$
06
#2655000
1$
16
b1 .
0&
b10 C
08
#2660000
0$
06
#2665000
1$
16
b10 .
1;
1,
#2670000
0$
06
#2675000
1$
16
b11 .
#2680000
0$
06
#2685000
1$
16
b100 .
#2690000
0$
06
#2695000
1$
16
b101 .
#2700000
0$
06
#2705000
1$
16
b110 .
#2710000
0$
06
#2715000
1$
16
b111 .
#2720000
0$
06
#2725000
1$
16
b1000 .
#2730000
0$
06
#2735000
1$
16
b1001 .
#2740000
0$
06
#2745000
1$
16
b1010 .
#2750000
0$
06
#2755000
1$
16
b1011 .
#2760000
0$
06
#2765000
1$
16
b1100 .
#2770000
0$
06
#2775000
1$
16
b1101 .
#2780000
0$
06
#2785000
1$
16
b1110 .
#2790000
0$
06
#2795000
1$
16
b1111 .
#2800000
0$
06
#2805000
1$
16
b10000 .
#2810000
0$
06
#2815000
1$
16
b10001 .
#2820000
0$
06
#2825000
1$
16
b10010 .
#2830000
0$
06
#2835000
1$
16
b10011 .
#2840000
0$
06
#2845000
1$
16
b0 .
1&
18
#2846000
b1 0
b10 1
#2850000
0$
06
#2855000
1$
16
b1 .
0&
b1 E
08
#2860000
0$
06
#2865000
1$
16
b10 .
0;
0,
#2870000
0$
06
#2875000
1$
16
b11 .
#2880000
0$
06
#2885000
1$
16
b100 .
#2890000
0$
06
#2895000
1$
16
b101 .
#2900000
0$
06
#2905000
1$
16
b110 .
#2910000
0$
06
#2915000
1$
16
b111 .
#2920000
0$
06
#2925000
1$
16
b1000 .
#2930000
0$
06
#2935000
1$
16
b1001 .
#2940000
0$
06
#2945000
1$
16
b1010 .
#2950000
0$
06
#2955000
1$
16
b1011 .
#2960000
0$
06
#2965000
1$
16
b1100 .
#2970000
0$
06
#2975000
1$
16
b1101 .
#2980000
0$
06
#2985000
1$
16
b1110 .
#2990000
0$
06
#2995000
1$
16
b1111 .
#3000000
0$
06
#3005000
1$
16
b10000 .
#3010000
0$
06
#3015000
1$
16
b10001 .
#3020000
0$
06
#3025000
1$
16
b10010 .
#3030000
0$
06
#3035000
1$
16
b10011 .
#3040000
0$
06
#3045000
1$
16
b0 .
1&
18
#3046000
b10 0
#3050000
0$
06
#3055000
1$
16
b1 .
0&
b10 E
08
#3060000
0$
06
#3065000
1$
16
b10 .
1;
1,
#3070000
0$
06
#3075000
1$
16
b11 .
#3080000
0$
06
#3085000
1$
16
b100 .
#3090000
0$
06
#3095000
1$
16
b101 .
#3100000
0$
06
#3105000
1$
16
b110 .
#3110000
0$
06
#3115000
1$
16
b111 .
#3120000
0$
06
#3125000
1$
16
b1000 .
#3130000
0$
06
#3135000
1$
16
b1001 .
#3140000
0$
06
#3145000
1$
16
b1010 .
#3150000
0$
06
#3155000
1$
16
b1011 .
#3160000
0$
06
#3165000
1$
16
b1100 .
#3170000
0$
06
#3175000
1$
16
b1101 .
#3180000
0$
06
#3185000
1$
16
b1110 .
#3190000
0$
06
#3195000
1$
16
b1111 .
#3200000
0$
06
#3205000
1$
16
b10000 .
#3210000
0$
06
#3215000
1$
16
b10001 .
#3220000
0$
06
#3225000
1$
16
b10010 .
#3230000
0$
06
#3235000
1$
16
b10011 .
#3240000
0$
06
#3245000
1$
16
b0 .
1&
18
#3246000
b11 0
b1010 1
#3250000
0$
06
#3255000
1$
16
b1 .
0&
b11 E
08
#3260000
0$
06
#3265000
1$
16
b10 .
0;
0,
#3270000
0$
06
#3275000
1$
16
b11 .
#3280000
0$
06
#3285000
1$
16
b100 .
#3290000
0$
06
#3295000
1$
16
b101 .
#3300000
0$
06
#3305000
1$
16
b110 .
#3310000
0$
06
#3315000
1$
16
b111 .
#3320000
0$
06
#3325000
1$
16
b1000 .
#3330000
0$
06
#3335000
1$
16
b1001 .
#3340000
0$
06
#3345000
1$
16
b1010 .
